Workbook

Sheet Assumptions
A1: Namibia Rent-to-Own Fleet Model - Key Assumptions (Editable)
A3: Assumption | B3: Value | C3: Units | D3: Notes / Source
A4: Car unit cost | B4: 60000 | C4: N$ per car | D4: N$250,000 / 4 cars
A5: Monthly Gross revenue per car | B5: 30000 | C5: N$ / car / month
A6: Contract length | B6: 24 | C6: months | D6: Client contract length that doubles as trigger for the disposal (with no disposal revenue) of all vehicles.
A7: Procurement lead time | B7: 3 | C7: months | D7: Estimate time from vehicle order to start of operation
A8: Fuel expense per operating car (monthly) | B8: 13000 | C8: N$ / car / month | D8: Estimated fuel expense based on Swakopmund operations ratio of N$18,000 made for every N$7,000 spent on fuel
A9: Airtime expense per operating car (monthly) | B9: 290 | C9: N$ / car / month | D9: Airtime for yango drivers
A10: Carwash expense per operating car (monthly) | B10: 240 | C10: N$ / car / month
A11: Maintenance expense per active car (monthly) | B11: 2000 | C11: N$ / car / month | D11: Maintenance cost completely/partially included in salary expense. Should be indicated in any client contracts.
A12: Driver subsistence | B12: 1400 | C12: N$ / car / month | D12: For client upkeep. Part of offset (used to offset operating profit for contracts extended beyond 15months) funds accumulated paid as subsistence.
A13: Incidental repair reserve | B13: 1600 | C13: N$ / car / month | D13: Internal repair insurance. Part of access or offset (used to offset operating profit to for contracts extended beyond 15months) funds accumulated paid to reserve. to repair reserve
A14: Tracking device expense | B14: 970 | C14: N$ / car / month | D14: Monthly payment for 3 year contract. 1 tracking device & 1 dashcam.
A15: Cost of sales | B15: 19500 | C15: N$ / car / month | D15: fuel+airtime+carwash+maintenance+subsistence+repairs+tracking.
A16: Monthly Gross profit per car | B16: 10500 | C16: N$ / car / month | D16: Calculated = gross revenue less direct running costs before salary.
A17: Salary expense per operating car (monthly) | B17: 3000 | C17: N$ / car / month | D17: For General manager + Operations supervisor. Maintenance also drawn from salary.
A18: Total operating expenses per operating car (monthly) | B18: 22500 | C18: N$ / car / month | D18: Calculated = Cost of sales + Salary expense per operating car (monthly).
A19: Operating Profit | B19: 7500 | C19: N$ / car / month | D19: Calculated = Gross profit - Value for Operating Expense. Determine vehicle disposal within prescribed period.)
A20: Min reinvest purchase batch size | B20: 4 | C20: cars | D20: Orders are placed only when retained profits can fund the purchase of atleast 4 cars.
A21: Corporate income tax rate | B21: 0.32 | C21: % | D21: NAMRA rate for CC's
A22: Initial owner/investor equity | B22: 250000 | C22: N$ | D22: Initial funding from 1 company member for the first batch of 4 cars
... A24: Bank loan draw month (operating month index) | B24: 5 | C24: month # | D24: Bank loan request to be made after the first 4 months of operation.
A25: Bank monthly instalment (principal + interest) | B25: =-PMT(B32,B31,B23) | C25: N$ / month | D25: Monthly instalment modelled as PMT (fixed periodic repayment) at 10.00% p.a. over 54 months on N$250,000.
A26: Bank nominal annual interest rate | B26: 0.1 | C26: % | D26: Model uses prime-linked nominal annual rate. Prime rate anchor: Bank of Namibia (BoN) MPC statement (repo 6.50% -> prime expected 10.00%): Bank Windhoek published prime lending rate (10.000% effective 29 Dec 2025):
A27: Owner/investor equity injection (batch 2) | B27: 250000 | C27: N$ | D27: Additional N$250,000 from 1 company member to help fund the second batch of 8 cars
A28: Owner second injection month (operating month index) | B28: 5 | C28: month # | D28: Second phase of owner funding to be made after the first 4 months of operation
A29: Initial cars in operation (month 1) | B29: 4 | C29: cars | D29: Initial batch of 4 cars.
A30: Model horizon | B30: 60 | C30: months | D30: 5 years monthly.
A31: Bank loan term | B31: 54 | C31: months | D31: Uploaded PDF recommendation: 54-month amortising facility.
A32: Bank monthly interest rate | B32: =B26/12 | C32: % / month | D32: Calculated from the annual nominal rate.
A33: Bank payment start month | B33: 5 | C33: month # | D33: Aligned to the draw month per the uploaded PDF.
A34: Investor payout per car per month | B34: 3000 | C34: N$ / car / month | D34: Set aside N$3,000 per car per month for each N$250,000 owner/investor amount.
A35: Batch 1 investor payout start month | B35: 1 | C35: month # | D35: Payouts begin once the cars funded by the second owner/investor tranche start operating.
A36: Batch 2 investor payout start month | B36: 8 | C36: month # | D36: Payouts begin once the cars funded by the second owner/investor tranche start operating.

Sheet Fleet_Schedule
A1: Fleet schedule (all cars combined) - monthly counts
A2: Month # | B2: Fiscal Year | C2: Month in FY | D2: Cars Purchased (orders placed) | E2: Cars Delivered (start operating) | F2: Cars In Pipeline (not yet operating) | G2: Cars in Rent-to-Own Operation | H2: Total Cars | I2: Total Cars In Operation (Cummulative) | J2: Cars Disposed (end of month) | K2: Total Cars Disposed (Cummulative)
A3: 1 | B3: 1 | C3: 1 | D3: 0 | E3: =Assumptions!$B$29 | F3: 0 | G3: =Assumptions!$B$29 | H3: =$G3+$F3 | I3: =$E3 | J3: =IF($A4>Assumptions!$B$6,INDEX($E$3:$E$62,MATCH($A4-Assumptions!$B$6,$A$3:$A$62,0)),0) | K3: =$J3
A4: 2 | B4: 1 | C4: 2 | D4: =IF((Cash_Flow!$N3+IF($A4=Assumptions!$B$24,Assumptions!$B$23,0)+IF($A4=Assumptions!$B$23,Assumptions!$B$27,0))>=Assumptions!$B$4*Assumptions!$B$20,INT((Cash_Flow!$N3+IF($A4=Assumptions!$B$24,Assumptions!$B$23,0)+IF($A4=Assumptions!$B$28,Assumptions!$B$27,0))/Assumptions!$B$4),0) | E4: =IF($A4>Assumptions!$B$7,INDEX($D$3:$D$62,MATCH($A4-Assumptions!$B$7,$A$3:$A$62,0)),0) | F4: =$F3+$D4-$E4 | G4: =$G3+$E4-$J4 | H4: =$G4+$F4 | I4: =$I3+$E4 | J4: =IF($A5>Assumptions!$B$6,INDEX($E$3:$E$62,MATCH($A5-Assumptions!$B$6,$A$3:$A$62,0)),0) | K4: =$J4+$K3
A5: 3 | B5: 1 | C5: 3 | D5: =IF((Cash_Flow!$N4+IF($A5=Assumptions!$B$24,Assumptions!$B$23,0)+IF($A5=Assumptions!$B$23,Assumptions!$B$27,0))>=Assumptions!$B$4*Assumptions!$B$20,INT((Cash_Flow!$N4+IF($A5=Assumptions!$B$24,Assumptions!$B$23,0)+IF($A5=Assumptions!$B$28,Assumptions!$B$27,0))/Assumptions!$B$4),0) | E5: =IF($A5>Assumptions!$B$7,INDEX($D$3:$D$62,MATCH($A5-Assumptions!$B$7,$A$3:$A$62,0)),0) | F5: =$F4+$D5-$E5 | G5: =$G4+$E5-$J5 | H5: =$G5+$F5 | I5: =$I4+$E5 | J5: =IF($A6>Assumptions!$B$6,INDEX($E$3:$E$62,MATCH($A6-Assumptions!$B$6,$A$3:$A$62,0)),0) | K5: =$J5+$K4
A6: 4 | B6: 1 | C6: 4 | D6: =IF((Cash_Flow!$N5+IF($A6=Assumptions!$B$24,Assumptions!$B$23,0)+IF($A6=Assumptions!$B$23,Assumptions!$B$27,0))>=Assumptions!$B$4*Assumptions!$B$20,INT((Cash_Flow!$N5+IF($A6=Assumptions!$B$24,Assumptions!$B$23,0)+IF($A6=Assumptions!$B$28,Assumptions!$B$27,0))/Assumptions!$B$4),0) | E6: =IF($A6>Assumptions!$B$7,INDEX($D$3:$D$62,MATCH($A6-Assumptions!$B$7,$A$3:$A$62,0)),0) | F6: =$F5+$D6-$E6 | G6: =$G5+$E6-$J6 | H6: =$G6+$F6 | I6: =$I5+$E6 | J6: =IF($A7>Assumptions!$B$6,INDEX($E$3:$E$62,MATCH($A7-Assumptions!$B$6,$A$3:$A$62,0)),0) | K6: =$J6+$K5
A7: 5 | B7: 1 | C7: 5 | D7: =IF((Cash_Flow!$N6+IF($A7=Assumptions!$B$24,Assumptions!$B$23,0)+IF($A7=Assumptions!$B$23,Assumptions!$B$27,0))>=Assumptions!$B$4*Assumptions!$B$20,INT((Cash_Flow!$N6+IF($A7=Assumptions!$B$24,Assumptions!$B$23,0)+IF($A7=Assumptions!$B$28,Assumptions!$B$27,0))/Assumptions!$B$4),0) | E7: =IF($A7>Assumptions!$B$7,INDEX($D$3:$D$62,MATCH($A7-Assumptions!$B$7,$A$3:$A$62,0)),0) | F7: =$F6+$D7-$E7 | G7: =$G6+$E7-$J7 | H7: =$G7+$F7 | I7: =$I6+$E7 | J7: =IF($A8>Assumptions!$B$6,INDEX($E$3:$E$62,MATCH($A8-Assumptions!$B$6,$A$3:$A$62,0)),0) | K7: =$J7+$K6
A8: 6 | B8: 1 | C8: 6 | D8: =IF((Cash_Flow!$N7+IF($A8=Assumptions!$B$24,Assumptions!$B$23,0)+IF($A8=Assumptions!$B$23,Assumptions!$B$27,0))>=Assumptions!$B$4*Assumptions!$B$20,INT((Cash_Flow!$N7+IF($A8=Assumptions!$B$24,Assumptions!$B$23,0)+IF($A8=Assumptions!$B$28,Assumptions!$B$27,0))/Assumptions!$B$4),0) | E8: =IF($A8>Assumptions!$B$7,INDEX($D$3:$D$62,MATCH($A8-Assumptions!$B$7,$A$3:$A$62,0)),0) | F8: =$F7+$D8-$E8 | G8: =$G7+$E8-$J8 | H8: =$G8+$F8 | I8: =$I7+$E8 | J8: =IF($A9>Assumptions!$B$6,INDEX($E$3:$E$62,MATCH($A9-Assumptions!$B$6,$A$3:$A$62,0)),0) | K8: =$J8+$K7
A9: 7 | B9: 1 | C9: 7 | D9: =IF((Cash_Flow!$N8+IF($A9=Assumptions!$B$24,Assumptions!$B$23,0)+IF($A9=Assumptions!$B$23,Assumptions!$B$27,0))>=Assumptions!$B$4*Assumptions!$B$20,INT((Cash_Flow!$N8+IF($A9=Assumptions!$B$24,Assumptions!$B$23,0)+IF($A9=Assumptions!$B$28,Assumptions!$B$27,0))/Assumptions!$B$4),0) | E9: =IF($A9>Assumptions!$B$7,INDEX($D$3:$D$62,MATCH($A9-Assumptions!$B$7,$A$3:$A$62,0)),0) | F9: =$F8+$D9-$E9 | G9: =$G8+$E9-$J9 | H9: =$G9+$F9 | I9: =$I8+$E9 | J9: =IF($A10>Assumptions!$B$6,INDEX($E$3:$E$62,MATCH($A10-Assumptions!$B$6,$A$3:$A$62,0)),0) | K9: =$J9+$K8
A10: 8 | B10: 1 | C10: 8 | D10: =IF((Cash_Flow!$N9+IF($A10=Assumptions!$B$24,Assumptions!$B$23,0)+IF($A10=Assumptions!$B$23,Assumptions!$B$27,0))>=Assumptions!$B$4*Assumptions!$B$20,INT((Cash_Flow!$N9+IF($A10=Assumptions!$B$24,Assumptions!$B$23,0)+IF($A10=Assumptions!$B$28,Assumptions!$B$27,0))/Assumptions!$B$4),0) | E10: =IF($A10>Assumptions!$B$7,INDEX($D$3:$D$62,MATCH($A10-Assumptions!$B$7,$A$3:$A$62,0)),0) | F10: =$F9+$D10-$E10 | G10: =$G9+$E10-$J10 | H10: =$G10+$F10 | I10: =$I9+$E10 | J10: =IF($A11>Assumptions!$B$6,INDEX($E$3:$E$62,MATCH($A11-Assumptions!$B$6,$A$3:$A$62,0)),0) | K10: =$J10+$K9
A11: 9 | B11: 1 | C11: 9 | D11: =IF((Cash_Flow!$N10+IF($A11=Assumptions!$B$24,Assumptions!$B$23,0)+IF($A11=Assumptions!$B$23,Assumptions!$B$27,0))>=Assumptions!$B$4*Assumptions!$B$20,INT((Cash_Flow!$N10+IF($A11=Assumptions!$B$24,Assumptions!$B$23,0)+IF($A11=Assumptions!$B$28,Assumptions!$B$27,0))/Assumptions!$B$4),0) | E11: =IF($A11>Assumptions!$B$7,INDEX($D$3:$D$62,MATCH($A11-Assumptions!$B$7,$A$3:$A$62,0)),0) | F11: =$F10+$D11-$E11 | G11: =$G10+$E11-$J11 | H11: =$G11+$F11 | I11: =$I10+$E11 | J11: =IF($A12>Assumptions!$B$6,INDEX($E$3:$E$62,MATCH($A12-Assumptions!$B$6,$A$3:$A$62,0)),0) | K11: =$J11+$K10
A12: 10 | B12: 1 | C12: 10 | D12: =IF((Cash_Flow!$N11+IF($A12=Assumptions!$B$24,Assumptions!$B$23,0)+IF($A12=Assumptions!$B$23,Assumptions!$B$27,0))>=Assumptions!$B$4*Assumptions!$B$20,INT((Cash_Flow!$N11+IF($A12=Assumptions!$B$24,Assumptions!$B$23,0)+IF($A12=Assumptions!$B$28,Assumptions!$B$27,0))/Assumptions!$B$4),0) | E12: =IF($A12>Assumptions!$B$7,INDEX($D$3:$D$62,MATCH($A12-Assumptions!$B$7,$A$3:$A$62,0)),0) | F12: =$F11+$D12-$E12 | G12: =$G11+$E12-$J12 | H12: =$G12+$F12 | I12: =$I11+$E12 | J12: =IF($A13>Assumptions!$B$6,INDEX($E$3:$E$62,MATCH($A13-Assumptions!$B$6,$A$3:$A$62,0)),0) | K12: =$J12+$K11
A13: 11 | B13: 1 | C13: 11 | D13: =IF((Cash_Flow!$N12+IF($A13=Assumptions!$B$24,Assumptions!$B$23,0)+IF($A13=Assumptions!$B$23,Assumptions!$B$27,0))>=Assumptions!$B$4*Assumptions!$B$20,INT((Cash_Flow!$N12+IF($A13=Assumptions!$B$24,Assumptions!$B$23,0)+IF($A13=Assumptions!$B$28,Assumptions!$B$27,0))/Assumptions!$B$4),0) | E13: =IF($A13>Assumptions!$B$7,INDEX($D$3:$D$62,MATCH($A13-Assumptions!$B$7,$A$3:$A$62,0)),0) | F13: =$F12+$D13-$E13 | G13: =$G12+$E13-$J13 | H13: =$G13+$F13 | I13: =$I12+$E13 | J13: =IF($A14>Assumptions!$B$6,INDEX($E$3:$E$62,MATCH($A14-Assumptions!$B$6,$A$3:$A$62,0)),0) | K13: =$J13+$K12
A14: 12 | B14: 1 | C14: 12 | D14: =IF((Cash_Flow!$N13+IF($A14=Assumptions!$B$24,Assumptions!$B$23,0)+IF($A14=Assumptions!$B$23,Assumptions!$B$27,0))>=Assumptions!$B$4*Assumptions!$B$20,INT((Cash_Flow!$N13+IF($A14=Assumptions!$B$24,Assumptions!$B$23,0)+IF($A14=Assumptions!$B$28,Assumptions!$B$27,0))/Assumptions!$B$4),0) | E14: =IF($A14>Assumptions!$B$7,INDEX($D$3:$D$62,MATCH($A14-Assumptions!$B$7,$A$3:$A$62,0)),0) | F14: =$F13+$D14-$E14 | G14: =$G13+$E14-$J14 | H14: =$G14+$F14 | I14: =$I13+$E14 | J14: =IF($A15>Assumptions!$B$6,INDEX($E$3:$E$62,MATCH($A15-Assumptions!$B$6,$A$3:$A$62,0)),0) | K14: =$J14+$K13
A15: 13 | B15: 2 | C15: 1 | D15: =IF((Cash_Flow!$N14+IF($A15=Assumptions!$B$24,Assumptions!$B$23,0)+IF($A15=Assumptions!$B$23,Assumptions!$B$27,0))>=Assumptions!$B$4*Assumptions!$B$20,INT((Cash_Flow!$N14+IF($A15=Assumptions!$B$24,Assumptions!$B$23,0)+IF($A15=Assumptions!$B$28,Assumptions!$B$27,0))/Assumptions!$B$4),0) | E15: =IF($A15>Assumptions!$B$7,INDEX($D$3:$D$62,MATCH($A15-Assumptions!$B$7,$A$3:$A$62,0)),0) | F15: =$F14+$D15-$E15 | G15: =$G14+$E15-$J15 | H15: =$G15+$F15 | I15: =$I14+$E15 | J15: =IF($A16>Assumptions!$B$6,INDEX($E$3:$E$62,MATCH($A16-Assumptions!$B$6,$A$3:$A$62,0)),0) | K15: =$J15+$K14
... A62: 60 | B62: 5 | C62: 12 | D62: =IF((Cash_Flow!$N61+IF($A62=Assumptions!$B$24,Assumptions!$B$23,0)+IF($A62=Assumptions!$B$23,Assumptions!$B$27,0))>=Assumptions!$B$4*Assumptions!$B$20,INT((Cash_Flow!$N61+IF($A62=Assumptions!$B$24,Assumptions!$B$23,0)+IF($A62=Assumptions!$B$28,Assumptions!$B$27,0))/Assumptions!$B$4),0) | E62: =IF($A62>Assumptions!$B$7,INDEX($D$3:$D$62,MATCH($A62-Assumptions!$B$7,$A$3:$A$62,0)),0) | F62: =$F61+$D62-$E62 | G62: =$G61+$E62-$J62 | H62: =$G62+$F62 | I62: =$I61+$E62 | J62: =IF($A63>Assumptions!$B$6,INDEX($E$3:$E$62,MATCH($A63-Assumptions!$B$6,$A$3:$A$62,0)),0) | K62: =$J62+$K61

Sheet Cash_Flow
A1: Monthly Cash Flow
A2: Month # | B2: Owner/Investor Injection | C2: Bank Loan Draw | D2: Total Cash In | E2: Operating Expenses (cash) | F2: Interest | G2: Loan Principal | H2: Income Tax Paid | I2: Investor Payout/Profit Distribution | J2: Net Cash Before Capex | K2: Capex (car purchases) | L2: Net Cash Flow | M2: Retained Profits Opening | N2: Retained Profits Closing | O2: Loan Opening | P2: Loan Closing
A3: 1 | B3: =Assumptions!$B$22 | C3: =IF($A3=Assumptions!$B$24,Assumptions!$B$23,0) | D3: =(Fleet_Schedule!$G3*Assumptions!$B$5)+SUM(C3) | E3: =Fleet_Schedule!G3*Assumptions!$B$18 | F3: =IF(AND($A3>=Assumptions!$B$33,$A3<Assumptions!$B$33+Assumptions!$B$31),($O3+$C3)*Assumptions!$B$32,0) | G3: =IF(AND($A3>=Assumptions!$B$33,$A3<Assumptions!$B$33+Assumptions!$B$31),MIN(($O3+$C3),Assumptions!$B$25-$F3),0) | H3: =Income_Statement!$S3 | I3: =IF($A3<Assumptions!$B$36,Assumptions!$B$34*Fleet_Schedule!$G3,ROUND(Assumptions!$B$34*(Fleet_Schedule!$G3-(Assumptions!$B$23/Assumptions!$B$4)),0)) | J3: =D3-E3-F3-G3-H3-I3 | K3: =Fleet_Schedule!$D3*Assumptions!$B$4 | L3: =J3-K3 | M3: 0 | N3: =$M3+$L3 | O3: 0 | P3: =O3+C3-G3
A4: 2 | B4: =IF($A4=Assumptions!$B$28,Assumptions!$B$27,0) | C4: =IF($A4=Assumptions!$B$24,Assumptions!$B$23,0) | D4: =(Fleet_Schedule!$G4*Assumptions!$B$5)+SUM(B4:C4) | E4: =Fleet_Schedule!G4*Assumptions!$B$18 | F4: =IF(AND($A4>=Assumptions!$B$33,$A4<Assumptions!$B$33+Assumptions!$B$31),($O4+$C4)*Assumptions!$B$32,0) | G4: =IF(AND($A4>=Assumptions!$B$33,$A4<Assumptions!$B$33+Assumptions!$B$31),MIN(($O4+$C4),Assumptions!$B$25-$F4),0) | H4: =Income_Statement!$S4 | I4: =IF($A4<Assumptions!$B$36,Assumptions!$B$34*Fleet_Schedule!$G4,ROUND(Assumptions!$B$34*(Fleet_Schedule!$G4-(Assumptions!$B$23/Assumptions!$B$4)),0)) | J4: =D4-E4-F4-G4-H4-I4 | K4: =Fleet_Schedule!$D4*Assumptions!$B$4 | L4: =J4-K4 | M4: =$N3 | N4: =$M4+$L4 | O4: =P3 | P4: =O4+C4-G4
A5: 3 | B5: =IF($A5=Assumptions!$B$28,Assumptions!$B$27,0) | C5: =IF($A5=Assumptions!$B$24,Assumptions!$B$23,0) | D5: =(Fleet_Schedule!$G5*Assumptions!$B$5)+SUM(B5:C5) | E5: =Fleet_Schedule!G5*Assumptions!$B$18 | F5: =IF(AND($A5>=Assumptions!$B$33,$A5<Assumptions!$B$33+Assumptions!$B$31),($O5+$C5)*Assumptions!$B$32,0) | G5: =IF(AND($A5>=Assumptions!$B$33,$A5<Assumptions!$B$33+Assumptions!$B$31),MIN(($O5+$C5),Assumptions!$B$25-$F5),0) | H5: =Income_Statement!$S5 | I5: =IF($A5<Assumptions!$B$36,Assumptions!$B$34*Fleet_Schedule!$G5,ROUND(Assumptions!$B$34*(Fleet_Schedule!$G5-(Assumptions!$B$23/Assumptions!$B$4)),0)) | J5: =D5-E5-F5-G5-H5-I5 | K5: =Fleet_Schedule!$D5*Assumptions!$B$4 | L5: =J5-K5 | M5: =$N4 | N5: =$M5+$L5 | O5: =P4 | P5: =O5+C5-G5
A6: 4 | B6: =IF($A6=Assumptions!$B$28,Assumptions!$B$27,0) | C6: =IF($A6=Assumptions!$B$24,Assumptions!$B$23,0) | D6: =(Fleet_Schedule!$G6*Assumptions!$B$5)+SUM(B6:C6) | E6: =Fleet_Schedule!G6*Assumptions!$B$18 | F6: =IF(AND($A6>=Assumptions!$B$33,$A6<Assumptions!$B$33+Assumptions!$B$31),($O6+$C6)*Assumptions!$B$32,0) | G6: =IF(AND($A6>=Assumptions!$B$33,$A6<Assumptions!$B$33+Assumptions!$B$31),MIN(($O6+$C6),Assumptions!$B$25-$F6),0) | H6: =Income_Statement!$S6 | I6: =IF($A6<Assumptions!$B$36,Assumptions!$B$34*Fleet_Schedule!$G6,ROUND(Assumptions!$B$34*(Fleet_Schedule!$G6-(Assumptions!$B$23/Assumptions!$B$4)),0)) | J6: =D6-E6-F6-G6-H6-I6 | K6: =Fleet_Schedule!$D6*Assumptions!$B$4 | L6: =J6-K6 | M6: =$N5 | N6: =$M6+$L6 | O6: =P5 | P6: =O6+C6-G6
A7: 5 | B7: =IF($A7=Assumptions!$B$28,Assumptions!$B$27,0) | C7: =IF($A7=Assumptions!$B$24,Assumptions!$B$23,0) | D7: =(Fleet_Schedule!$G7*Assumptions!$B$5)+SUM(B7:C7) | E7: =Fleet_Schedule!G7*Assumptions!$B$18 | F7: =IF(AND($A7>=Assumptions!$B$33,$A7<Assumptions!$B$33+Assumptions!$B$31),($O7+$C7)*Assumptions!$B$32,0) | G7: =IF(AND($A7>=Assumptions!$B$33,$A7<Assumptions!$B$33+Assumptions!$B$31),MIN(($O7+$C7),Assumptions!$B$25-$F7),0) | H7: =Income_Statement!$S7 | I7: =IF($A7<Assumptions!$B$36,Assumptions!$B$34*Fleet_Schedule!$G7,ROUND(Assumptions!$B$34*(Fleet_Schedule!$G7-(Assumptions!$B$23/Assumptions!$B$4)),0)) | J7: =D7-E7-F7-G7-H7-I7 | K7: =Fleet_Schedule!$D7*Assumptions!$B$4 | L7: =J7-K7 | M7: =$N6 | N7: =$M7+$L7 | O7: =P6 | P7: =O7+C7-G7
A8: 6 | B8: =IF($A8=Assumptions!$B$28,Assumptions!$B$27,0) | C8: =IF($A8=Assumptions!$B$24,Assumptions!$B$23,0) | D8: =(Fleet_Schedule!$G8*Assumptions!$B$5)+SUM(B8:C8) | E8: =Fleet_Schedule!G8*Assumptions!$B$18 | F8: =IF(AND($A8>=Assumptions!$B$33,$A8<Assumptions!$B$33+Assumptions!$B$31),($O8+$C8)*Assumptions!$B$32,0) | G8: =IF(AND($A8>=Assumptions!$B$33,$A8<Assumptions!$B$33+Assumptions!$B$31),MIN(($O8+$C8),Assumptions!$B$25-$F8),0) | H8: =Income_Statement!$S8 | I8: =IF($A8<Assumptions!$B$36,Assumptions!$B$34*Fleet_Schedule!$G8,ROUND(Assumptions!$B$34*(Fleet_Schedule!$G8-(Assumptions!$B$23/Assumptions!$B$4)),0)) | J8: =D8-E8-F8-G8-H8-I8 | K8: =Fleet_Schedule!$D8*Assumptions!$B$4 | L8: =J8-K8 | M8: =$N7 | N8: =$M8+$L8 | O8: =P7 | P8: =O8+C8-G8
A9: 7 | B9: =IF($A9=Assumptions!$B$28,Assumptions!$B$27,0) | C9: =IF($A9=Assumptions!$B$24,Assumptions!$B$23,0) | D9: =(Fleet_Schedule!$G9*Assumptions!$B$5)+SUM(B9:C9) | E9: =Fleet_Schedule!G9*Assumptions!$B$18 | F9: =IF(AND($A9>=Assumptions!$B$33,$A9<Assumptions!$B$33+Assumptions!$B$31),($O9+$C9)*Assumptions!$B$32,0) | G9: =IF(AND($A9>=Assumptions!$B$33,$A9<Assumptions!$B$33+Assumptions!$B$31),MIN(($O9+$C9),Assumptions!$B$25-$F9),0) | H9: =Income_Statement!$S9 | I9: =IF($A9<Assumptions!$B$36,Assumptions!$B$34*Fleet_Schedule!$G9,ROUND(Assumptions!$B$34*(Fleet_Schedule!$G9-(Assumptions!$B$23/Assumptions!$B$4)),0)) | J9: =D9-E9-F9-G9-H9-I9 | K9: =Fleet_Schedule!$D9*Assumptions!$B$4 | L9: =J9-K9 | M9: =$N8 | N9: =$M9+$L9 | O9: =P8 | P9: =O9+C9-G9
A10: 8 | B10: =IF($A10=Assumptions!$B$28,Assumptions!$B$27,0) | C10: =IF($A10=Assumptions!$B$24,Assumptions!$B$23,0) | D10: =(Fleet_Schedule!$G10*Assumptions!$B$5)+SUM(B10:C10) | E10: =Fleet_Schedule!G10*Assumptions!$B$18 | F10: =IF(AND($A10>=Assumptions!$B$33,$A10<Assumptions!$B$33+Assumptions!$B$31),($O10+$C10)*Assumptions!$B$32,0) | G10: =IF(AND($A10>=Assumptions!$B$33,$A10<Assumptions!$B$33+Assumptions!$B$31),MIN(($O10+$C10),Assumptions!$B$25-$F10),0) | H10: =Income_Statement!$S10 | I10: =IF($A10<Assumptions!$B$36,Assumptions!$B$34*Fleet_Schedule!$G10,ROUND(Assumptions!$B$34*(Fleet_Schedule!$G10-(Assumptions!$B$23/Assumptions!$B$4)),0)) | J10: =D10-E10-F10-G10-H10-I10 | K10: =Fleet_Schedule!$D10*Assumptions!$B$4 | L10: =J10-K10 | M10: =$N9 | N10: =$M10+$L10 | O10: =P9 | P10: =O10+C10-G10
A11: 9 | B11: =IF($A11=Assumptions!$B$28,Assumptions!$B$27,0) | C11: =IF($A11=Assumptions!$B$24,Assumptions!$B$23,0) | D11: =(Fleet_Schedule!$G11*Assumptions!$B$5)+SUM(B11:C11) | E11: =Fleet_Schedule!G11*Assumptions!$B$18 | F11: =IF(AND($A11>=Assumptions!$B$33,$A11<Assumptions!$B$33+Assumptions!$B$31),($O11+$C11)*Assumptions!$B$32,0) | G11: =IF(AND($A11>=Assumptions!$B$33,$A11<Assumptions!$B$33+Assumptions!$B$31),MIN(($O11+$C11),Assumptions!$B$25-$F11),0) | H11: =Income_Statement!$S11 | I11: =IF($A11<Assumptions!$B$36,Assumptions!$B$34*Fleet_Schedule!$G11,ROUND(Assumptions!$B$34*(Fleet_Schedule!$G11-(Assumptions!$B$23/Assumptions!$B$4)),0)) | J11: =D11-E11-F11-G11-H11-I11 | K11: =Fleet_Schedule!$D11*Assumptions!$B$4 | L11: =J11-K11 | M11: =$N10 | N11: =$M11+$L11 | O11: =P10 | P11: =O11+C11-G11
A12: 10 | B12: =IF($A12=Assumptions!$B$28,Assumptions!$B$27,0) | C12: =IF($A12=Assumptions!$B$24,Assumptions!$B$23,0) | D12: =(Fleet_Schedule!$G12*Assumptions!$B$5)+SUM(B12:C12) | E12: =Fleet_Schedule!G12*Assumptions!$B$18 | F12: =IF(AND($A12>=Assumptions!$B$33,$A12<Assumptions!$B$33+Assumptions!$B$31),($O12+$C12)*Assumptions!$B$32,0) | G12: =IF(AND($A12>=Assumptions!$B$33,$A12<Assumptions!$B$33+Assumptions!$B$31),MIN(($O12+$C12),Assumptions!$B$25-$F12),0) | H12: =Income_Statement!$S12 | I12: =IF($A12<Assumptions!$B$36,Assumptions!$B$34*Fleet_Schedule!$G12,ROUND(Assumptions!$B$34*(Fleet_Schedule!$G12-(Assumptions!$B$23/Assumptions!$B$4)),0)) | J12: =D12-E12-F12-G12-H12-I12 | K12: =Fleet_Schedule!$D12*Assumptions!$B$4 | L12: =J12-K12 | M12: =$N11 | N12: =$M12+$L12 | O12: =P11 | P12: =O12+C12-G12
A13: 11 | B13: =IF($A13=Assumptions!$B$28,Assumptions!$B$27,0) | C13: =IF($A13=Assumptions!$B$24,Assumptions!$B$23,0) | D13: =(Fleet_Schedule!$G13*Assumptions!$B$5)+SUM(B13:C13) | E13: =Fleet_Schedule!G13*Assumptions!$B$18 | F13: =IF(AND($A13>=Assumptions!$B$33,$A13<Assumptions!$B$33+Assumptions!$B$31),($O13+$C13)*Assumptions!$B$32,0) | G13: =IF(AND($A13>=Assumptions!$B$33,$A13<Assumptions!$B$33+Assumptions!$B$31),MIN(($O13+$C13),Assumptions!$B$25-$F13),0) | H13: =Income_Statement!$S13 | I13: =IF($A13<Assumptions!$B$36,Assumptions!$B$34*Fleet_Schedule!$G13,ROUND(Assumptions!$B$34*(Fleet_Schedule!$G13-(Assumptions!$B$23/Assumptions!$B$4)),0)) | J13: =D13-E13-F13-G13-H13-I13 | K13: =Fleet_Schedule!$D13*Assumptions!$B$4 | L13: =J13-K13 | M13: =$N12 | N13: =$M13+$L13 | O13: =P12 | P13: =O13+C13-G13
A14: 12 | B14: =IF($A14=Assumptions!$B$28,Assumptions!$B$27,0) | C14: =IF($A14=Assumptions!$B$24,Assumptions!$B$23,0) | D14: =(Fleet_Schedule!$G14*Assumptions!$B$5)+SUM(B14:C14) | E14: =Fleet_Schedule!G14*Assumptions!$B$18 | F14: =IF(AND($A14>=Assumptions!$B$33,$A14<Assumptions!$B$33+Assumptions!$B$31),($O14+$C14)*Assumptions!$B$32,0) | G14: =IF(AND($A14>=Assumptions!$B$33,$A14<Assumptions!$B$33+Assumptions!$B$31),MIN(($O14+$C14),Assumptions!$B$25-$F14),0) | H14: =Income_Statement!$S14 | I14: =IF($A14<Assumptions!$B$36,Assumptions!$B$34*Fleet_Schedule!$G14,ROUND(Assumptions!$B$34*(Fleet_Schedule!$G14-(Assumptions!$B$23/Assumptions!$B$4)),0)) | J14: =D14-E14-F14-G14-H14-I14 | K14: =Fleet_Schedule!$D14*Assumptions!$B$4 | L14: =J14-K14 | M14: =$N13 | N14: =$M14+$L14 | O14: =P13 | P14: =O14+C14-G14
A15: 13 | B15: =IF($A15=Assumptions!$B$28,Assumptions!$B$27,0) | C15: =IF($A15=Assumptions!$B$24,Assumptions!$B$23,0) | D15: =(Fleet_Schedule!$G15*Assumptions!$B$5)+SUM(B15:C15) | E15: =Fleet_Schedule!G15*Assumptions!$B$18 | F15: =IF(AND($A15>=Assumptions!$B$33,$A15<Assumptions!$B$33+Assumptions!$B$31),($O15+$C15)*Assumptions!$B$32,0) | G15: =IF(AND($A15>=Assumptions!$B$33,$A15<Assumptions!$B$33+Assumptions!$B$31),MIN(($O15+$C15),Assumptions!$B$25-$F15),0) | H15: =Income_Statement!$S15 | I15: =IF($A15<Assumptions!$B$36,Assumptions!$B$34*Fleet_Schedule!$G15,ROUND(Assumptions!$B$34*(Fleet_Schedule!$G15-(Assumptions!$B$23/Assumptions!$B$4)),0)) | J15: =D15-E15-F15-G15-H15-I15 | K15: =Fleet_Schedule!$D15*Assumptions!$B$4 | L15: =J15-K15 | M15: =$N14 | N15: =$M15+$L15 | O15: =P14 | P15: =O15+C15-G15
... A62: 60 | B62: =IF($A62=Assumptions!$B$28,Assumptions!$B$27,0) | C62: =IF($A62=Assumptions!$B$24,Assumptions!$B$23,0) | D62: =(Fleet_Schedule!$G62*Assumptions!$B$5)+SUM(B62:C62) | E62: =Fleet_Schedule!G62*Assumptions!$B$18 | F62: =IF(AND($A62>=Assumptions!$B$33,$A62<Assumptions!$B$33+Assumptions!$B$31),($O62+$C62)*Assumptions!$B$32,0) | G62: =IF(AND($A62>=Assumptions!$B$33,$A62<Assumptions!$B$33+Assumptions!$B$31),MIN(($O62+$C62),Assumptions!$B$25-$F62),0) | H62: =Income_Statement!$S62 | I62: =IF($A62<Assumptions!$B$36,Assumptions!$B$34*Fleet_Schedule!$G62,ROUND(Assumptions!$B$34*(Fleet_Schedule!$G62-(Assumptions!$B$23/Assumptions!$B$4)),0)) | J62: =D62-E62-F62-G62-H62-I62 | K62: =Fleet_Schedule!$D62*Assumptions!$B$4 | L62: =J62-K62 | M62: =$N61 | N62: =$M62+$L62 | O62: =P61 | P62: =O62+C62-G62

Sheet Income_Statement
A1: Monthly Income Statement
A2: Year # | B2: Month # | C2: Cars in Operation | D2: Monthly Gross Revenue | E2: Fuel | F2: Airtime | G2: Carwash | H2: Maintenance | I2: Driver Subsistence Allocation | J2: Incidental Repair Reserve | K2: Tracking Device | L2: Cost of Sales | M2: Gross Profit | N2: Salary | O2: Total Operating Expenses | P2: Operating Profit (EBIT) | Q2: Interest Expense | R2: Profit Before Tax | S2: Income Tax | T2: Net Profit | U2: Investor Payout/Profit Distribution | V2: Retained Profits
A3: 1 | B3: 1 | C3: =Fleet_Schedule!$G3 | D3: =$C3*Assumptions!$B$5 | E3: =$C3*Assumptions!$B$8 | F3: =$C3*Assumptions!$B$9 | G3: =$C3*Assumptions!$B$10 | H3: =$C3*Assumptions!$B$11 | I3: =$C3*Assumptions!$B$12 | J3: =$C3*Assumptions!$B$13 | K3: =$C3*Assumptions!$B$14 | L3: =SUM(E3:K3) | M3: =D3-L3 | N3: =$C3*Assumptions!$B$17 | O3: =SUM(N3) | P3: =M3-O3 | Q3: =Cash_Flow!$F3 | R3: =$P3-$Q3 | S3: =Assumptions!$B$21*MAX(0,$R3) | T3: =$R3-$S3 | U3: =Cash_Flow!$I3 | V3: =$T3-$U3
A4: 1 | B4: 2 | C4: =Fleet_Schedule!$G4 | D4: =$C4*Assumptions!$B$5 | E4: =$C4*Assumptions!$B$8 | F4: =$C4*Assumptions!$B$9 | G4: =$C4*Assumptions!$B$10 | H4: =$C4*Assumptions!$B$11 | I4: =$C4*Assumptions!$B$12 | J4: =$C4*Assumptions!$B$13 | K4: =$C4*Assumptions!$B$14 | L4: =SUM(E4:K4) | M4: =D4-L4 | N4: =$C4*Assumptions!$B$17 | O4: =SUM(N4) | P4: =M4-O4 | Q4: =Cash_Flow!$F4 | R4: =$P4-$Q4 | S4: =Assumptions!$B$21*MAX(0,$R4) | T4: =$R4-$S4 | U4: =Cash_Flow!$I4 | V4: =$T4-$U4
A5: 1 | B5: 3 | C5: =Fleet_Schedule!$G5 | D5: =$C5*Assumptions!$B$5 | E5: =$C5*Assumptions!$B$8 | F5: =$C5*Assumptions!$B$9 | G5: =$C5*Assumptions!$B$10 | H5: =$C5*Assumptions!$B$11 | I5: =$C5*Assumptions!$B$12 | J5: =$C5*Assumptions!$B$13 | K5: =$C5*Assumptions!$B$14 | L5: =SUM(E5:K5) | M5: =D5-L5 | N5: =$C5*Assumptions!$B$17 | O5: =SUM(N5) | P5: =M5-O5 | Q5: =Cash_Flow!$F5 | R5: =$P5-$Q5 | S5: =Assumptions!$B$21*MAX(0,$R5) | T5: =$R5-$S5 | U5: =Cash_Flow!$I5 | V5: =$T5-$U5
A6: 1 | B6: 4 | C6: =Fleet_Schedule!$G6 | D6: =$C6*Assumptions!$B$5 | E6: =$C6*Assumptions!$B$8 | F6: =$C6*Assumptions!$B$9 | G6: =$C6*Assumptions!$B$10 | H6: =$C6*Assumptions!$B$11 | I6: =$C6*Assumptions!$B$12 | J6: =$C6*Assumptions!$B$13 | K6: =$C6*Assumptions!$B$14 | L6: =SUM(E6:K6) | M6: =D6-L6 | N6: =$C6*Assumptions!$B$17 | O6: =SUM(N6) | P6: =M6-O6 | Q6: =Cash_Flow!$F6 | R6: =$P6-$Q6 | S6: =Assumptions!$B$21*MAX(0,$R6) | T6: =$R6-$S6 | U6: =Cash_Flow!$I6 | V6: =$T6-$U6
A7: 1 | B7: 5 | C7: =Fleet_Schedule!$G7 | D7: =$C7*Assumptions!$B$5 | E7: =$C7*Assumptions!$B$8 | F7: =$C7*Assumptions!$B$9 | G7: =$C7*Assumptions!$B$10 | H7: =$C7*Assumptions!$B$11 | I7: =$C7*Assumptions!$B$12 | J7: =$C7*Assumptions!$B$13 | K7: =$C7*Assumptions!$B$14 | L7: =SUM(E7:K7) | M7: =D7-L7 | N7: =$C7*Assumptions!$B$17 | O7: =SUM(N7) | P7: =M7-O7 | Q7: =Cash_Flow!$F7 | R7: =$P7-$Q7 | S7: =Assumptions!$B$21*MAX(0,$R7) | T7: =$R7-$S7 | U7: =Cash_Flow!$I7 | V7: =$T7-$U7
A8: 1 | B8: 6 | C8: =Fleet_Schedule!$G8 | D8: =$C8*Assumptions!$B$5 | E8: =$C8*Assumptions!$B$8 | F8: =$C8*Assumptions!$B$9 | G8: =$C8*Assumptions!$B$10 | H8: =$C8*Assumptions!$B$11 | I8: =$C8*Assumptions!$B$12 | J8: =$C8*Assumptions!$B$13 | K8: =$C8*Assumptions!$B$14 | L8: =SUM(E8:K8) | M8: =D8-L8 | N8: =$C8*Assumptions!$B$17 | O8: =SUM(N8) | P8: =M8-O8 | Q8: =Cash_Flow!$F8 | R8: =$P8-$Q8 | S8: =Assumptions!$B$21*MAX(0,$R8) | T8: =$R8-$S8 | U8: =Cash_Flow!$I8 | V8: =$T8-$U8
A9: 1 | B9: 7 | C9: =Fleet_Schedule!$G9 | D9: =$C9*Assumptions!$B$5 | E9: =$C9*Assumptions!$B$8 | F9: =$C9*Assumptions!$B$9 | G9: =$C9*Assumptions!$B$10 | H9: =$C9*Assumptions!$B$11 | I9: =$C9*Assumptions!$B$12 | J9: =$C9*Assumptions!$B$13 | K9: =$C9*Assumptions!$B$14 | L9: =SUM(E9:K9) | M9: =D9-L9 | N9: =$C9*Assumptions!$B$17 | O9: =SUM(N9) | P9: =M9-O9 | Q9: =Cash_Flow!$F9 | R9: =$P9-$Q9 | S9: =Assumptions!$B$21*MAX(0,$R9) | T9: =$R9-$S9 | U9: =Cash_Flow!$I9 | V9: =$T9-$U9
A10: 1 | B10: 8 | C10: =Fleet_Schedule!$G10 | D10: =$C10*Assumptions!$B$5 | E10: =$C10*Assumptions!$B$8 | F10: =$C10*Assumptions!$B$9 | G10: =$C10*Assumptions!$B$10 | H10: =$C10*Assumptions!$B$11 | I10: =$C10*Assumptions!$B$12 | J10: =$C10*Assumptions!$B$13 | K10: =$C10*Assumptions!$B$14 | L10: =SUM(E10:K10) | M10: =D10-L10 | N10: =$C10*Assumptions!$B$17 | O10: =SUM(N10) | P10: =M10-O10 | Q10: =Cash_Flow!$F10 | R10: =$P10-$Q10 | S10: =Assumptions!$B$21*MAX(0,$R10) | T10: =$R10-$S10 | U10: =Cash_Flow!$I10 | V10: =$T10-$U10
A11: 1 | B11: 9 | C11: =Fleet_Schedule!$G11 | D11: =$C11*Assumptions!$B$5 | E11: =$C11*Assumptions!$B$8 | F11: =$C11*Assumptions!$B$9 | G11: =$C11*Assumptions!$B$10 | H11: =$C11*Assumptions!$B$11 | I11: =$C11*Assumptions!$B$12 | J11: =$C11*Assumptions!$B$13 | K11: =$C11*Assumptions!$B$14 | L11: =SUM(E11:K11) | M11: =D11-L11 | N11: =$C11*Assumptions!$B$17 | O11: =SUM(N11) | P11: =M11-O11 | Q11: =Cash_Flow!$F11 | R11: =$P11-$Q11 | S11: =Assumptions!$B$21*MAX(0,$R11) | T11: =$R11-$S11 | U11: =Cash_Flow!$I11 | V11: =$T11-$U11
A12: 1 | B12: 10 | C12: =Fleet_Schedule!$G12 | D12: =$C12*Assumptions!$B$5 | E12: =$C12*Assumptions!$B$8 | F12: =$C12*Assumptions!$B$9 | G12: =$C12*Assumptions!$B$10 | H12: =$C12*Assumptions!$B$11 | I12: =$C12*Assumptions!$B$12 | J12: =$C12*Assumptions!$B$13 | K12: =$C12*Assumptions!$B$14 | L12: =SUM(E12:K12) | M12: =D12-L12 | N12: =$C12*Assumptions!$B$17 | O12: =SUM(N12) | P12: =M12-O12 | Q12: =Cash_Flow!$F12 | R12: =$P12-$Q12 | S12: =Assumptions!$B$21*MAX(0,$R12) | T12: =$R12-$S12 | U12: =Cash_Flow!$I12 | V12: =$T12-$U12
A13: 1 | B13: 11 | C13: =Fleet_Schedule!$G13 | D13: =$C13*Assumptions!$B$5 | E13: =$C13*Assumptions!$B$8 | F13: =$C13*Assumptions!$B$9 | G13: =$C13*Assumptions!$B$10 | H13: =$C13*Assumptions!$B$11 | I13: =$C13*Assumptions!$B$12 | J13: =$C13*Assumptions!$B$13 | K13: =$C13*Assumptions!$B$14 | L13: =SUM(E13:K13) | M13: =D13-L13 | N13: =$C13*Assumptions!$B$17 | O13: =SUM(N13) | P13: =M13-O13 | Q13: =Cash_Flow!$F13 | R13: =$P13-$Q13 | S13: =Assumptions!$B$21*MAX(0,$R13) | T13: =$R13-$S13 | U13: =Cash_Flow!$I13 | V13: =$T13-$U13
A14: 1 | B14: 12 | C14: =Fleet_Schedule!$G14 | D14: =$C14*Assumptions!$B$5 | E14: =$C14*Assumptions!$B$8 | F14: =$C14*Assumptions!$B$9 | G14: =$C14*Assumptions!$B$10 | H14: =$C14*Assumptions!$B$11 | I14: =$C14*Assumptions!$B$12 | J14: =$C14*Assumptions!$B$13 | K14: =$C14*Assumptions!$B$14 | L14: =SUM(E14:K14) | M14: =D14-L14 | N14: =$C14*Assumptions!$B$17 | O14: =SUM(N14) | P14: =M14-O14 | Q14: =Cash_Flow!$F14 | R14: =$P14-$Q14 | S14: =Assumptions!$B$21*MAX(0,$R14) | T14: =$R14-$S14 | U14: =Cash_Flow!$I14 | V14: =$T14-$U14
... A62: 5 | B62: 60 | C62: =Fleet_Schedule!$G62 | D62: =$C62*Assumptions!$B$5 | E62: =$C62*Assumptions!$B$8 | F62: =$C62*Assumptions!$B$9 | G62: =$C62*Assumptions!$B$10 | H62: =$C62*Assumptions!$B$11 | I62: =$C62*Assumptions!$B$12 | J62: =$C62*Assumptions!$B$13 | K62: =$C62*Assumptions!$B$14 | L62: =SUM(E62:K62) | M62: =D62-L62 | N62: =$C62*Assumptions!$B$17 | O62: =SUM(N62) | P62: =M62-O62 | Q62: =Cash_Flow!$F62 | R62: =$P62-$Q62 | S62: =Assumptions!$B$21*MAX(0,$R62) | T62: =$R62-$S62 | U62: =Cash_Flow!$I62 | V62: =$T62-$U62

Sheet Balance_Sheet
B1: Monthly Balance Sheet Snapshot
A2: Year # | B2: Month # | C2: Total Owner/Investor Capital Invested | D2: Net Owner/Investor Capital Outstanding | E2: Loan Closing Balance | F2: Cars in Operation (count) | G2: Total Cars Operation (Cummulative) | H2: Vehicles In Use - Cost | I2: Total Cars Cost (Cummulative) | J2: Net Cash Before Capex | K2: Capex (car purchases) | L2: Gross Revenue (Cummulative) | M2: Operating Expenses (Cummulative) | N2: Operating Profit (Cummulative) | O2: Loan Repayment (Cummulative) | P2: Income Tax | Q2: Income Tax (Cummulative) | R2: Net Profit (Cummulative) | S2: Investor Payout/Profit Distribution | T2: Net Profit | U2: Investor Payout/Profit Distribution (Cummulative) | V2: Retained Profits Closing | W2: Retained Profits (Cummulative)
A3: 1 | B3: 1 | C3: =IF($A3>1,0,Assumptions!$B$22+IF($B3>4,Assumptions!$B$27,0)) | D3: =IF($U3>(Assumptions!$B$22 + Assumptions!$B$23),0,IF($B3>4,(Assumptions!$B$22+Assumptions!$B$27)-$U3,Assumptions!$B$22-$U3)) | E3: =Cash_Flow!$P3 | F3: =Fleet_Schedule!$G3 | G3: =Fleet_Schedule!$I3 | H3: =$F3*Assumptions!$B$4 | I3: =$G3*Assumptions!$B$4 | J3: =Cash_Flow!$J3 | K3: =Cash_Flow!$K3 | L3: =$F3*Assumptions!$B$5 | M3: =Cash_Flow!$E3 | N3: =Income_Statement!$P3 | O3: =(Cash_Flow!$F3+Cash_Flow!$G3) | P3: =Income_Statement!$S3 | Q3: =Income_Statement!$S3 | R3: =Income_Statement!$T3 | S3: =Income_Statement!$U3 | T3: =Income_Statement!$T3 | U3: =Income_Statement!$U3 | V3: =Cash_Flow!$N3 | W3: =Cash_Flow!$N3
A4: 1 | B4: 2 | C4: =IF($A4>1,0,Assumptions!$B$22+IF($B4>4,Assumptions!$B$27,0)) | D4: =IF($U4>(Assumptions!$B$22 + Assumptions!$B$23),0,IF($B4>4,(Assumptions!$B$22+Assumptions!$B$27)-$U4,Assumptions!$B$22-$U4)) | E4: =Cash_Flow!$P4 | F4: =Fleet_Schedule!$G4 | G4: =Fleet_Schedule!$I4 | H4: =$F4*Assumptions!$B$4 | I4: =$G4*Assumptions!$B$4 | J4: =Cash_Flow!$J4 | K4: =Cash_Flow!$K4 | L4: =L3+(F4*Assumptions!$B$5) | M4: =$M3+Cash_Flow!$E4 | N4: =$N3+Income_Statement!$P4 | O4: =IF(Cash_Flow!$F4<=0,0,$O3+(Cash_Flow!$F4+Cash_Flow!$G4)) | P4: =Income_Statement!$S4 | Q4: =$Q3+Income_Statement!$S4 | R4: =$R3+Income_Statement!$T4 | S4: =Income_Statement!$U4 | T4: =Income_Statement!$T4 | U4: =$U3+Income_Statement!$U4 | V4: =Cash_Flow!$N4 | W4: =($W3+Cash_Flow!$J4)-(Cash_Flow!$B4+Cash_Flow!$C4)
A5: 1 | B5: 3 | C5: =IF($A5>1,0,Assumptions!$B$22+IF($B5>4,Assumptions!$B$27,0)) | D5: =IF($U5>(Assumptions!$B$22 + Assumptions!$B$23),0,IF($B5>4,(Assumptions!$B$22+Assumptions!$B$27)-$U5,Assumptions!$B$22-$U5)) | E5: =Cash_Flow!$P5 | F5: =Fleet_Schedule!$G5 | G5: =Fleet_Schedule!$I5 | H5: =$F5*Assumptions!$B$4 | I5: =$G5*Assumptions!$B$4 | J5: =Cash_Flow!$J5 | K5: =Cash_Flow!$K5 | L5: =L4+(F5*Assumptions!$B$5) | M5: =$M4+Cash_Flow!$E5 | N5: =$N4+Income_Statement!$P5 | O5: =IF(Cash_Flow!$F5<=0,0,$O4+(Cash_Flow!$F5+Cash_Flow!$G5)) | P5: =Income_Statement!$S5 | Q5: =$Q4+Income_Statement!$S5 | R5: =$R4+Income_Statement!$T5 | S5: =Income_Statement!$U5 | T5: =Income_Statement!$T5 | U5: =$U4+Income_Statement!$U5 | V5: =Cash_Flow!$N5 | W5: =($W4+Cash_Flow!$J5)-(Cash_Flow!$B5+Cash_Flow!$C5)
A6: 1 | B6: 4 | C6: =IF($A6>1,0,Assumptions!$B$22+IF($B6>4,Assumptions!$B$27,0)) | D6: =IF($U6>(Assumptions!$B$22 + Assumptions!$B$23),0,IF($B6>4,(Assumptions!$B$22+Assumptions!$B$27)-$U6,Assumptions!$B$22-$U6)) | E6: =Cash_Flow!$P6 | F6: =Fleet_Schedule!$G6 | G6: =Fleet_Schedule!$I6 | H6: =$F6*Assumptions!$B$4 | I6: =$G6*Assumptions!$B$4 | J6: =Cash_Flow!$J6 | K6: =Cash_Flow!$K6 | L6: =L5+(F6*Assumptions!$B$5) | M6: =$M5+Cash_Flow!$E6 | N6: =$N5+Income_Statement!$P6 | O6: =IF(Cash_Flow!$F6<=0,0,$O5+(Cash_Flow!$F6+Cash_Flow!$G6)) | P6: =Income_Statement!$S6 | Q6: =$Q5+Income_Statement!$S6 | R6: =$R5+Income_Statement!$T6 | S6: =Income_Statement!$U6 | T6: =Income_Statement!$T6 | U6: =$U5+Income_Statement!$U6 | V6: =Cash_Flow!$N6 | W6: =($W5+Cash_Flow!$J6)-(Cash_Flow!$B6+Cash_Flow!$C6)
A7: 1 | B7: 5 | C7: =IF($A7>1,0,Assumptions!$B$22+IF($B7>4,Assumptions!$B$27,0)) | D7: =IF($U7>(Assumptions!$B$22 + Assumptions!$B$23),0,IF($B7>4,(Assumptions!$B$22+Assumptions!$B$27)-$U7,Assumptions!$B$22-$U7)) | E7: =Cash_Flow!$P7 | F7: =Fleet_Schedule!$G7 | G7: =Fleet_Schedule!$I7 | H7: =$F7*Assumptions!$B$4 | I7: =$G7*Assumptions!$B$4 | J7: =Cash_Flow!$J7 | K7: =Cash_Flow!$K7 | L7: =L6+(F7*Assumptions!$B$5) | M7: =$M6+Cash_Flow!$E7 | N7: =$N6+Income_Statement!$P7 | O7: =IF(Cash_Flow!$F7<=0,0,$O6+(Cash_Flow!$F7+Cash_Flow!$G7)) | P7: =Income_Statement!$S7 | Q7: =$Q6+Income_Statement!$S7 | R7: =$R6+Income_Statement!$T7 | S7: =Income_Statement!$U7 | T7: =Income_Statement!$T7 | U7: =$U6+Income_Statement!$U7 | V7: =Cash_Flow!$N7 | W7: =($W6+Cash_Flow!$J7)-(Cash_Flow!$B7+Cash_Flow!$C7)
A8: 1 | B8: 6 | C8: =IF($A8>1,0,Assumptions!$B$22+IF($B8>4,Assumptions!$B$27,0)) | D8: =IF($U8>(Assumptions!$B$22 + Assumptions!$B$23),0,IF($B8>4,(Assumptions!$B$22+Assumptions!$B$27)-$U8,Assumptions!$B$22-$U8)) | E8: =Cash_Flow!$P8 | F8: =Fleet_Schedule!$G8 | G8: =Fleet_Schedule!$I8 | H8: =$F8*Assumptions!$B$4 | I8: =$G8*Assumptions!$B$4 | J8: =Cash_Flow!$J8 | K8: =Cash_Flow!$K8 | L8: =L7+(F8*Assumptions!$B$5) | M8: =$M7+Cash_Flow!$E8 | N8: =$N7+Income_Statement!$P8 | O8: =IF(Cash_Flow!$F8<=0,0,$O7+(Cash_Flow!$F8+Cash_Flow!$G8)) | P8: =Income_Statement!$S8 | Q8: =$Q7+Income_Statement!$S8 | R8: =$R7+Income_Statement!$T8 | S8: =Income_Statement!$U8 | T8: =Income_Statement!$T8 | U8: =$U7+Income_Statement!$U8 | V8: =Cash_Flow!$N8 | W8: =($W7+Cash_Flow!$J8)-(Cash_Flow!$B8+Cash_Flow!$C8)
A9: 1 | B9: 7 | C9: =IF($A9>1,0,Assumptions!$B$22+IF($B9>4,Assumptions!$B$27,0)) | D9: =IF($U9>(Assumptions!$B$22 + Assumptions!$B$23),0,IF($B9>4,(Assumptions!$B$22+Assumptions!$B$27)-$U9,Assumptions!$B$22-$U9)) | E9: =Cash_Flow!$P9 | F9: =Fleet_Schedule!$G9 | G9: =Fleet_Schedule!$I9 | H9: =$F9*Assumptions!$B$4 | I9: =$G9*Assumptions!$B$4 | J9: =Cash_Flow!$J9 | K9: =Cash_Flow!$K9 | L9: =L8+(F9*Assumptions!$B$5) | M9: =$M8+Cash_Flow!$E9 | N9: =$N8+Income_Statement!$P9 | O9: =IF(Cash_Flow!$F9<=0,0,$O8+(Cash_Flow!$F9+Cash_Flow!$G9)) | P9: =Income_Statement!$S9 | Q9: =$Q8+Income_Statement!$S9 | R9: =$R8+Income_Statement!$T9 | S9: =Income_Statement!$U9 | T9: =Income_Statement!$T9 | U9: =$U8+Income_Statement!$U9 | V9: =Cash_Flow!$N9 | W9: =($W8+Cash_Flow!$J9)-(Cash_Flow!$B9+Cash_Flow!$C9)
A10: 1 | B10: 8 | C10: =IF($A10>1,0,Assumptions!$B$22+IF($B10>4,Assumptions!$B$27,0)) | D10: =IF($U10>(Assumptions!$B$22 + Assumptions!$B$23),0,IF($B10>4,(Assumptions!$B$22+Assumptions!$B$27)-$U10,Assumptions!$B$22-$U10)) | E10: =Cash_Flow!$P10 | F10: =Fleet_Schedule!$G10 | G10: =Fleet_Schedule!$I10 | H10: =$F10*Assumptions!$B$4 | I10: =$G10*Assumptions!$B$4 | J10: =Cash_Flow!$J10 | K10: =Cash_Flow!$K10 | L10: =L9+(F10*Assumptions!$B$5) | M10: =$M9+Cash_Flow!$E10 | N10: =$N9+Income_Statement!$P10 | O10: =IF(Cash_Flow!$F10<=0,0,$O9+(Cash_Flow!$F10+Cash_Flow!$G10)) | P10: =Income_Statement!$S10 | Q10: =$Q9+Income_Statement!$S10 | R10: =$R9+Income_Statement!$T10 | S10: =Income_Statement!$U10 | T10: =Income_Statement!$T10 | U10: =$U9+Income_Statement!$U10 | V10: =Cash_Flow!$N10 | W10: =($W9+Cash_Flow!$J10)-(Cash_Flow!$B10+Cash_Flow!$C10)
A11: 1 | B11: 9 | C11: =IF($A11>1,0,Assumptions!$B$22+IF($B11>4,Assumptions!$B$27,0)) | D11: =IF($U11>(Assumptions!$B$22 + Assumptions!$B$23),0,IF($B11>4,(Assumptions!$B$22+Assumptions!$B$27)-$U11,Assumptions!$B$22-$U11)) | E11: =Cash_Flow!$P11 | F11: =Fleet_Schedule!$G11 | G11: =Fleet_Schedule!$I11 | H11: =$F11*Assumptions!$B$4 | I11: =$G11*Assumptions!$B$4 | J11: =Cash_Flow!$J11 | K11: =Cash_Flow!$K11 | L11: =L10+(F11*Assumptions!$B$5) | M11: =$M10+Cash_Flow!$E11 | N11: =$N10+Income_Statement!$P11 | O11: =IF(Cash_Flow!$F11<=0,0,$O10+(Cash_Flow!$F11+Cash_Flow!$G11)) | P11: =Income_Statement!$S11 | Q11: =$Q10+Income_Statement!$S11 | R11: =$R10+Income_Statement!$T11 | S11: =Income_Statement!$U11 | T11: =Income_Statement!$T11 | U11: =$U10+Income_Statement!$U11 | V11: =Cash_Flow!$N11 | W11: =($W10+Cash_Flow!$J11)-(Cash_Flow!$B11+Cash_Flow!$C11)
A12: 1 | B12: 10 | C12: =IF($A12>1,0,Assumptions!$B$22+IF($B12>4,Assumptions!$B$27,0)) | D12: =IF($U12>(Assumptions!$B$22 + Assumptions!$B$23),0,IF($B12>4,(Assumptions!$B$22+Assumptions!$B$27)-$U12,Assumptions!$B$22-$U12)) | E12: =Cash_Flow!$P12 | F12: =Fleet_Schedule!$G12 | G12: =Fleet_Schedule!$I12 | H12: =$F12*Assumptions!$B$4 | I12: =$G12*Assumptions!$B$4 | J12: =Cash_Flow!$J12 | K12: =Cash_Flow!$K12 | L12: =L11+(F12*Assumptions!$B$5) | M12: =$M11+Cash_Flow!$E12 | N12: =$N11+Income_Statement!$P12 | O12: =IF(Cash_Flow!$F12<=0,0,$O11+(Cash_Flow!$F12+Cash_Flow!$G12)) | P12: =Income_Statement!$S12 | Q12: =$Q11+Income_Statement!$S12 | R12: =$R11+Income_Statement!$T12 | S12: =Income_Statement!$U12 | T12: =Income_Statement!$T12 | U12: =$U11+Income_Statement!$U12 | V12: =Cash_Flow!$N12 | W12: =($W11+Cash_Flow!$J12)-(Cash_Flow!$B12+Cash_Flow!$C12)
A13: 1 | B13: 11 | C13: =IF($A13>1,0,Assumptions!$B$22+IF($B13>4,Assumptions!$B$27,0)) | D13: =IF($U13>(Assumptions!$B$22 + Assumptions!$B$23),0,IF($B13>4,(Assumptions!$B$22+Assumptions!$B$27)-$U13,Assumptions!$B$22-$U13)) | E13: =Cash_Flow!$P13 | F13: =Fleet_Schedule!$G13 | G13: =Fleet_Schedule!$I13 | H13: =$F13*Assumptions!$B$4 | I13: =$G13*Assumptions!$B$4 | J13: =Cash_Flow!$J13 | K13: =Cash_Flow!$K13 | L13: =L12+(F13*Assumptions!$B$5) | M13: =$M12+Cash_Flow!$E13 | N13: =$N12+Income_Statement!$P13 | O13: =IF(Cash_Flow!$F13<=0,0,$O12+(Cash_Flow!$F13+Cash_Flow!$G13)) | P13: =Income_Statement!$S13 | Q13: =$Q12+Income_Statement!$S13 | R13: =$R12+Income_Statement!$T13 | S13: =Income_Statement!$U13 | T13: =Income_Statement!$T13 | U13: =$U12+Income_Statement!$U13 | V13: =Cash_Flow!$N13 | W13: =($W12+Cash_Flow!$J13)-(Cash_Flow!$B13+Cash_Flow!$C13)
A14: 1 | B14: 12 | C14: =IF($A14>1,0,Assumptions!$B$22+IF($B14>4,Assumptions!$B$27,0)) | D14: =IF($U14>(Assumptions!$B$22 + Assumptions!$B$23),0,IF($B14>4,(Assumptions!$B$22+Assumptions!$B$27)-$U14,Assumptions!$B$22-$U14)) | E14: =Cash_Flow!$P14 | F14: =Fleet_Schedule!$G14 | G14: =Fleet_Schedule!$I14 | H14: =$F14*Assumptions!$B$4 | I14: =$G14*Assumptions!$B$4 | J14: =Cash_Flow!$J14 | K14: =Cash_Flow!$K14 | L14: =L13+(F14*Assumptions!$B$5) | M14: =$M13+Cash_Flow!$E14 | N14: =$N13+Income_Statement!$P14 | O14: =IF(Cash_Flow!$F14<=0,0,$O13+(Cash_Flow!$F14+Cash_Flow!$G14)) | P14: =Income_Statement!$S14 | Q14: =$Q13+Income_Statement!$S14 | R14: =$R13+Income_Statement!$T14 | S14: =Income_Statement!$U14 | T14: =Income_Statement!$T14 | U14: =$U13+Income_Statement!$U14 | V14: =Cash_Flow!$N14 | W14: =($W13+Cash_Flow!$J14)-(Cash_Flow!$B14+Cash_Flow!$C14)
A15: 2 | B15: 13 | C15: =IF($A15>1,0,Assumptions!$B$22+IF($B15>4,Assumptions!$B$27,0)) | D15: =IF($U15>(Assumptions!$B$22 + Assumptions!$B$23),0,IF($B15>4,(Assumptions!$B$22+Assumptions!$B$27)-$U15,Assumptions!$B$22-$U15)) | E15: =Cash_Flow!$P15 | F15: =Fleet_Schedule!$G15 | G15: =Fleet_Schedule!$I15 | H15: =$F15*Assumptions!$B$4 | I15: =$G15*Assumptions!$B$4 | J15: =Cash_Flow!$J15 | K15: =Cash_Flow!$K15 | L15: =L14+(F15*Assumptions!$B$5) | M15: =$M14+Cash_Flow!$E15 | N15: =$N14+Income_Statement!$P15 | O15: =IF(Cash_Flow!$F15<=0,0,$O14+(Cash_Flow!$F15+Cash_Flow!$G15)) | P15: =Income_Statement!$S15 | Q15: =$Q14+Income_Statement!$S15 | R15: =$R14+Income_Statement!$T15 | S15: =Income_Statement!$U15 | T15: =Income_Statement!$T15 | U15: =$U14+Income_Statement!$U15 | V15: =Cash_Flow!$N15 | W15: =($W14+Cash_Flow!$J15)-(Cash_Flow!$B15+Cash_Flow!$C15)
... A62: 5 | B62: 60 | C62: =IF($A62>1,0,Assumptions!$B$22+IF($B62>4,Assumptions!$B$27,0)) | D62: =IF($U62>(Assumptions!$B$22 + Assumptions!$B$23),0,IF($B62>4,(Assumptions!$B$22+Assumptions!$B$27)-$U62,Assumptions!$B$22-$U62)) | E62: =Cash_Flow!$P62 | F62: =Fleet_Schedule!$G62 | G62: =Fleet_Schedule!$I62 | H62: =$F62*Assumptions!$B$4 | I62: =$G62*Assumptions!$B$4 | J62: =Cash_Flow!$J62 | K62: =Cash_Flow!$K62 | L62: =L61+(F62*Assumptions!$B$5) | M62: =$M61+Cash_Flow!$E62 | N62: =$N61+Income_Statement!$P62 | O62: =IF(Cash_Flow!$F62<=0,0,$O61+(Cash_Flow!$F62+Cash_Flow!$G62)) | P62: =Income_Statement!$S62 | Q62: =$Q61+Income_Statement!$S62 | R62: =$R61+Income_Statement!$T62 | S62: =Income_Statement!$U62 | T62: =Income_Statement!$T62 | U62: =$U61+Income_Statement!$U62 | V62: =Cash_Flow!$N62 | W62: =($W61+Cash_Flow!$J62)-(Cash_Flow!$B62+Cash_Flow!$C62)

Sheet Loan_Amortisation
A1: Loan Amortisation - linked to Cash_Flow
A2: Prime-linked amortising bank facility: N$250,000 at 10.00% p.a. over 54 months, with payments starting in operating month 5. Opening balance includes the draw in the first loan month.
A4: Loan month | B4: Opening balance | C4: Interest | D4: Principal | E4: Payment | F4: Closing balance
A5: 1 | B5: =INDEX(Cash_Flow!$O$3:$O$62,MATCH(Assumptions!$B$33+A5-1,Cash_Flow!$A$3:$A$62,0))+INDEX(Cash_Flow!$C$3:$C$62,MATCH(Assumptions!$B$33+A5-1,Cash_Flow!$A$3:$A$62,0)) | C5: =INDEX(Cash_Flow!$F:$F,MATCH(Assumptions!$B$28+A5-1,Cash_Flow!$A:$A,0)) | D5: =INDEX(Cash_Flow!$G:$G,MATCH(Assumptions!$B$28+A5-1,Cash_Flow!$A:$A,0)) | E5: =C5+D5 | F5: =MAX(0,B5-D5)
A6: 2 | B6: =F5 | C6: =INDEX(Cash_Flow!$F:$F,MATCH(Assumptions!$B$28+A6-1,Cash_Flow!$A:$A,0)) | D6: =INDEX(Cash_Flow!$G:$G,MATCH(Assumptions!$B$28+A6-1,Cash_Flow!$A:$A,0)) | E6: =C6+D6 | F6: =MAX(0,B6-D6)
A7: 3 | B7: =F6 | C7: =INDEX(Cash_Flow!$F:$F,MATCH(Assumptions!$B$28+A7-1,Cash_Flow!$A:$A,0)) | D7: =INDEX(Cash_Flow!$G:$G,MATCH(Assumptions!$B$28+A7-1,Cash_Flow!$A:$A,0)) | E7: =C7+D7 | F7: =MAX(0,B7-D7)
A8: 4 | B8: =F7 | C8: =INDEX(Cash_Flow!$F:$F,MATCH(Assumptions!$B$28+A8-1,Cash_Flow!$A:$A,0)) | D8: =INDEX(Cash_Flow!$G:$G,MATCH(Assumptions!$B$28+A8-1,Cash_Flow!$A:$A,0)) | E8: =C8+D8 | F8: =MAX(0,B8-D8)
A9: 5 | B9: =F8 | C9: =INDEX(Cash_Flow!$F:$F,MATCH(Assumptions!$B$28+A9-1,Cash_Flow!$A:$A,0)) | D9: =INDEX(Cash_Flow!$G:$G,MATCH(Assumptions!$B$28+A9-1,Cash_Flow!$A:$A,0)) | E9: =C9+D9 | F9: =MAX(0,B9-D9)
A10: 6 | B10: =F9 | C10: =INDEX(Cash_Flow!$F:$F,MATCH(Assumptions!$B$28+A10-1,Cash_Flow!$A:$A,0)) | D10: =INDEX(Cash_Flow!$G:$G,MATCH(Assumptions!$B$28+A10-1,Cash_Flow!$A:$A,0)) | E10: =C10+D10 | F10: =MAX(0,B10-D10)
A11: 7 | B11: =F10 | C11: =INDEX(Cash_Flow!$F:$F,MATCH(Assumptions!$B$28+A11-1,Cash_Flow!$A:$A,0)) | D11: =INDEX(Cash_Flow!$G:$G,MATCH(Assumptions!$B$28+A11-1,Cash_Flow!$A:$A,0)) | E11: =C11+D11 | F11: =MAX(0,B11-D11)
A12: 8 | B12: =F11 | C12: =INDEX(Cash_Flow!$F:$F,MATCH(Assumptions!$B$28+A12-1,Cash_Flow!$A:$A,0)) | D12: =INDEX(Cash_Flow!$G:$G,MATCH(Assumptions!$B$28+A12-1,Cash_Flow!$A:$A,0)) | E12: =C12+D12 | F12: =MAX(0,B12-D12)
A13: 9 | B13: =F12 | C13: =INDEX(Cash_Flow!$F:$F,MATCH(Assumptions!$B$28+A13-1,Cash_Flow!$A:$A,0)) | D13: =INDEX(Cash_Flow!$G:$G,MATCH(Assumptions!$B$28+A13-1,Cash_Flow!$A:$A,0)) | E13: =C13+D13 | F13: =MAX(0,B13-D13)
A14: 10 | B14: =F13 | C14: =INDEX(Cash_Flow!$F:$F,MATCH(Assumptions!$B$28+A14-1,Cash_Flow!$A:$A,0)) | D14: =INDEX(Cash_Flow!$G:$G,MATCH(Assumptions!$B$28+A14-1,Cash_Flow!$A:$A,0)) | E14: =C14+D14 | F14: =MAX(0,B14-D14)
A15: 11 | B15: =F14 | C15: =INDEX(Cash_Flow!$F:$F,MATCH(Assumptions!$B$28+A15-1,Cash_Flow!$A:$A,0)) | D15: =INDEX(Cash_Flow!$G:$G,MATCH(Assumptions!$B$28+A15-1,Cash_Flow!$A:$A,0)) | E15: =C15+D15 | F15: =MAX(0,B15-D15)
A16: 12 | B16: =F15 | C16: =INDEX(Cash_Flow!$F:$F,MATCH(Assumptions!$B$28+A16-1,Cash_Flow!$A:$A,0)) | D16: =INDEX(Cash_Flow!$G:$G,MATCH(Assumptions!$B$28+A16-1,Cash_Flow!$A:$A,0)) | E16: =C16+D16 | F16: =MAX(0,B16-D16)
A17: 13 | B17: =F16 | C17: =INDEX(Cash_Flow!$F:$F,MATCH(Assumptions!$B$28+A17-1,Cash_Flow!$A:$A,0)) | D17: =INDEX(Cash_Flow!$G:$G,MATCH(Assumptions!$B$28+A17-1,Cash_Flow!$A:$A,0)) | E17: =C17+D17 | F17: =MAX(0,B17-D17)
... A58: 54 | B58: =F57 | C58: =INDEX(Cash_Flow!$F:$F,MATCH(Assumptions!$B$28+A58-1,Cash_Flow!$A:$A,0)) | D58: =INDEX(Cash_Flow!$G:$G,MATCH(Assumptions!$B$28+A58-1,Cash_Flow!$A:$A,0)) | E58: =C58+D58 | F58: =MAX(0,B58-D58)
